{
  "type": "FeatureCollection",
  "features": [
    {
      "geometry": {
        "type": "Point",
        "coordinates": [
          -73.59123229980469,
          45.482882442969554
        ]
      },
      "properties": {
        "marker-symbol": 1,
        "title": "Driver 1",
        "driverId": 1
      },
      "type": "Feature"
    },
    {
      "geometry": {
        "type": "Point",
        "coordinates": [
          -73.5565265,
          45.5089229
        ]
      },
      "properties": {
        "orderId": 1,
        "stopKind": 0,
        "marker-symbol": "p",
        "marker-color": "#f00",
        "title": "Montreal City Hall",
        "start": 0
      },
      "type": "Feature"
    },
    {
      "geometry": {
        "type": "Point",
        "coordinates": [
          -73.624615,
          45.5316767
        ]
      },
      "properties": {
        "orderId": 1,
        "stopKind": 1,
        "marker-symbol": "d",
        "marker-color": "#f00",
        "title": "Apcurium Group Inc",
        "start": 0
      },
      "type": "Feature"
    },
    {
      "geometry": {
        "type": "Point",
        "coordinates": [
          -73.553861,
          45.5047707
        ]
      },
      "properties": {
        "orderId": 2,
        "stopKind": 0,
        "marker-symbol": "p",
        "marker-color": "#0a0",
        "title": "Montreal Science Centre",
        "start": 10800
      },
      "type": "Feature"
    },
    {
      "geometry": {
        "type": "Point",
        "coordinates": [
          -73.54076385498047,
          45.472591097387046
        ]
      },
      "properties": {
        "marker-symbol": "d",
        "marker-color": "#0a0",
        "orderId": 2,
        "stopKind": 1,
        "start": 10800
      },
      "type": "Feature"
    },
    {
      "geometry": {
        "type": "Point",
        "coordinates": [
          -73.56432437896729,
          45.50730933674183
        ]
      },
      "properties": {
        "marker-color": "#00c",
        "marker-symbol": "p",
        "orderId": 3,
        "stopKind": 0,
        "start": 10800
      },
      "type": "Feature"
    },
    {
      "geometry": {
        "type": "Point",
        "coordinates": [
          -73.5771131515503,
          45.493653241464465
        ]
      },
      "properties": {
        "marker-color": "#00c",
        "marker-symbol": "d",
        "orderId": 3,
        "stopKind": 1,
        "start": 10800
      },
      "type": "Feature"
    },
    {
      "geometry": {
        "type": "Point",
        "coordinates": [
          -73.55741500854492,
          45.49648098683461
        ]
      },
      "properties": {
        "marker-symbol": 2,
        "title": "Driver 2",
        "marker-color": "",
        "driverId": 2
      },
      "type": "Feature"
    },
    {
      "geometry": {
        "type": "Point",
        "coordinates": [
          -73.63019943237305,
          45.49789480627276
        ]
      },
      "properties": {
        "marker-symbol": "p",
        "marker-color": "#c0c",
        "orderId": 4,
        "stopKind": 0,
        "start": 0
      },
      "type": "Feature"
    },
    {
      "geometry": {
        "type": "Point",
        "coordinates": [
          -73.58161926269531,
          45.50810634131551
        ]
      },
      "properties": {
        "marker-symbol": "d",
        "marker-color": "#c0c",
        "orderId": 4,
        "stopKind": 1,
        "start": 0
      },
      "type": "Feature"
    },
    {
      "geometry": {
        "type": "Point",
        "coordinates": [
          -73.5791516304016,
          45.507204071143164
        ]
      },
      "properties": {
        "marker-symbol": "p",
        "marker-color": "#cc0",
        "orderId": 5,
        "stopKind": 0,
        "start": 0
      },
      "type": "Feature"
    },
    {
      "geometry": {
        "type": "Point",
        "coordinates": [
          -73.6384391784668,
          45.4580837290498
        ]
      },
      "properties": {
        "marker-symbol": "d",
        "marker-color": "#cc0",
        "orderId": 5,
        "stopKind": 1,
        "start": 0
      },
      "type": "Feature"
    },
    {
      "geometry": {
        "type": "Point",
        "coordinates": [
          -73.65659236907959,
          45.49807529130555
        ]
      },
      "properties": {
        "marker-symbol": "p",
        "marker-color": "#0cf",
        "orderId": 6,
        "stopKind": 0,
        "start": 0
      },
      "type": "Feature"
    },
    {
      "geometry": {
        "type": "Point",
        "coordinates": [
          -73.6225175857544,
          45.53220663801898
        ]
      },
      "properties": {
        "marker-symbol": "d",
        "marker-color": "#0cf",
        "orderId": 6,
        "stopKind": 1,
        "start": 0
      },
      "type": "Feature"
    }
  ]
}